qengine/__init__.py
qengine-0.0.2.dist-info/METADATA
qengine-0.0.2.dist-info/WHEEL
qengine-0.0.2.dist-info/licenses/LICENSE
qengine-0.0.2.dist-info/RECORD
